weather_agent/__init__.py
weather_agent/__main__.py
weather_agent/agent.py
weather_agent/cli.py
weather_agent/config.py
weather_agent/tools/__init__.py
weather_agent/tools/geocoding.py
weather_agent/tools/statistics.py
weather_agent/tools/weather_api.py
weather_agent/visualization/plotter.py
weather_ensemble_agent-0.1.1.dist-info/METADATA
weather_ensemble_agent-0.1.1.dist-info/WHEEL
weather_ensemble_agent-0.1.1.dist-info/entry_points.txt
weather_ensemble_agent-0.1.1.dist-info/licenses/LICENSE
weather_ensemble_agent-0.1.1.dist-info/RECORD
