Metadata-Version: 2.4
Name: weather-ensemble-agent
Version: 0.1.1
Summary: AI agent for ensemble weather forecast analysis using Claude and multiple weather models
Project-URL: Homepage, https://github.com/rmcd-mscb/weather-ensemble-agent
Project-URL: Repository, https://github.com/rmcd-mscb/weather-ensemble-agent
Project-URL: Issues, https://github.com/rmcd-mscb/weather-ensemble-agent/issues
Project-URL: Documentation, https://github.com/rmcd-mscb/weather-ensemble-agent#readme
Project-URL: Changelog, https://github.com/rmcd-mscb/weather-ensemble-agent/blob/main/CHANGELOG.md
Author-email: Richard McDonald <richard.mcdonald@connected-waters.com>
License: MIT
License-File: LICENSE
Keywords: agentic-ai,ai-agent,anthropic,claude,ensemble,forecast,llm,meteorology,tool-calling,weather
Classifier: Development Status :: 3 - Alpha
Classifier: Intended Audience :: Developers
Classifier: Intended Audience :: Science/Research
Classifier: License :: OSI Approved :: MIT License
Classifier: Programming Language :: Python :: 3
Classifier: Programming Language :: Python :: 3.12
Classifier: Topic :: Scientific/Engineering :: Artificial Intelligence
Classifier: Topic :: Scientific/Engineering :: Atmospheric Science
Classifier: Topic :: Software Development :: Libraries :: Python Modules
Requires-Python: >=3.12
Requires-Dist: anthropic>=0.75.0
Requires-Dist: cyclopts>=4.4.4
Requires-Dist: matplotlib>=3.10.8
Requires-Dist: numpy>=2.4.0
Requires-Dist: pydantic>=2.12.5
Requires-Dist: python-dotenv>=1.2.1
Requires-Dist: requests>=2.32.5
Requires-Dist: rich>=14.2.0
